sk_in_torch/__init__.py
sk_in_torch/linear_model.py
sk_in_torch/neighbors.py
sk_in_torch/neural_network.py
sk_in_torch-0.0.3.dist-info/METADATA
sk_in_torch-0.0.3.dist-info/WHEEL
sk_in_torch-0.0.3.dist-info/licenses/LICENSE
sk_in_torch-0.0.3.dist-info/RECORD
