Metadata-Version: 2.1
Name: sk_in_torch
Version: 0.0.3
Summary: Torch models rewritten in sklearn format
Project-URL: Homepage, https://github.com/HaoLi111/sk_in_torch/
Project-URL: Issues, https://github.com/HaoLi111/sk_in_torch/issues
Author-email: Hao Li <haolircplanes@gmail.com>
License-File: LICENSE
Classifier: License :: OSI Approved :: MIT License
Classifier: Operating System :: OS Independent
Classifier: Programming Language :: Python :: 3
Requires-Python: >=3.8
